spoc/__init__.py
spoc/bibtex.py
spoc/constants.py
spoc/protocols.conf
spoc/spoc_logo.png
spoc/wizards.py
spoc/protocols/__init__.py
spoc/protocols/protocol_confidence_map.py
spoc/protocols/protocol_fsc_fdr_control.py
spoc/tests/__init__.py
spoc/tests/test_protocols_spoc.py
spoc/viewers/__init__.py
spoc/viewers/viewer_confidence_map.py
spoc/viewers/viewer_fsc_fdr_control.py
scipion_em_spoc-1.0.6.dist-info/LICENSE
scipion_em_spoc-1.0.6.dist-info/METADATA
scipion_em_spoc-1.0.6.dist-info/WHEEL
scipion_em_spoc-1.0.6.dist-info/entry_points.txt
scipion_em_spoc-1.0.6.dist-info/top_level.txt
scipion_em_spoc-1.0.6.dist-info/RECORD
