Metadata-Version: 2.1
Name: scipion-em-spoc
Version: 1.0.6
Summary: Plugin to use SPOC programs within the Scipion framework
Home-page: https://github.com/scipion-em/scipion-em-spoc
Author: I2PC
Author-email: scipion@cnb.csic.es
License: UNKNOWN
Project-URL: Bug Reports, https://github.com/scipion-em/scipion-em-spoc/issues
Project-URL: Source, https://github.com/scipion-em/scipion-em-spoc/
Keywords: scipion electron-microscopy cryo-em structural-biology image-processing scipion-3.0
Platform: UNKNOWN
Classifier: Development Status :: 4 - Beta
Classifier: License :: OSI Approved :: GNU General Public License v3 (GPLv3)
Classifier: Programming Language :: Python :: 3
Requires-Dist: scipion-em
